[{"id":207,"name":"Наружная световая вывеска \"\"Пятерочка\"\"","text":"Реклама в магазине \\ Внешняя и внутренняя реклама \\ Наружная световая вывеска \"\"Пятерочка\"\"","deprecated":false,"editDate":1528385960435,"author":"asko"},{"id":208,"name":"Наружняя реклама на фасаде (растяжки, пленка)","text":"Реклама в магазине \\ Внешняя и внутренняя реклама \\ Наружняя реклама на фасаде (растяжки, пленка)","deprecated":false,"editDate":1528385960438,"author":"asko"},{"id":209,"name":"Навигация торгового зала (указатели, вывески)","text":"Реклама в магазине \\ Внешняя и внутренняя реклама \\ Навигация торгового зала (указатели, вывески)","deprecated":false,"editDate":1528385960442,"author":"asko"},{"id":216,"name":"Акционный баннер на фасаде","text":"Реклама в магазине \\ Внешняя и внутренняя реклама \\ Акционный баннер на фасаде","deprecated":false,"editDate":1528385960446,"author":"asko"}]